{"items":[{"type":"album","name":"Saal","url":"https://kmru.bandcamp.com/album/saal","imageUrl":"https://f4.bcbits.com/img/a1632003892_9.jpg","genre":"ambient","artist":{"name":"KMRU","url":"https://kmru.bandcamp.com","imageUrl":"https://f4.bcbits.com/img/24810541_21.jpg"},"location":"Nairobi, Kenya","featuredTrack":{"name":"Saal","duration":948,"streamUrl":{"mp3-128":"https://t4.bcbits.com/stream/281f797b9dbf902e10132a065ffc7db2/mp3-128/1180553868?p=0&ts=1668176745&t=e5c65de8f3550bbbcf8d43a1080ecd63f9257e54&token=1668176745_76ef48f52449c37ed7f711ff3b3fb5e3550923b6"}}},{"type":"album","name":"Blue Roofs","url":"https://nrv-nerve.bandcamp.com/album/blue-roofs","imageUrl":"https://f4.bcbits.com/img/a2769759753_9.jpg","genre":"ambient","artist":{"name":"NRV","url":"https://nrv-nerve.bandcamp.com","imageUrl":"https://f4.bcbits.com/img/24595134_21.jpg"},"location":"Japan","featuredTrack":{"name":"Blue Roofs","duration":1202.48,"streamUrl":{"mp3-128":"https://t4.bcbits.com/stream/cd8c8f4d62e644017963c7f2a05c8355/mp3-128/3986662811?p=0&ts=1668176745&t=56428f94e239ebf1ef8242c44d73aed47ad19448&token=1668176745_dc557319a8a2d9c937a9d859f90890660c448497"}}},{"type":"album","name":"Where the floor starts to fade","url":"https://vrcc.bandcamp.com/album/where-the-floor-starts-to-fade","imageUrl":"https://f4.bcbits.com/img/a1783662363_9.jpg","genre":"ambient","artist":{"name":"Velvet Rope Crowd Control","url":"https://vrcc.bandcamp.com","imageUrl":"https://f4.bcbits.com/img/null_21.jpg"},"location":null,"featuredTrack":{"name":"Opening Night","duration":243.961,"streamUrl":{"mp3-128":"https://t4.bcbits.com/stream/6cbc6b7e4ecaffbba1d13dcfa2256f89/mp3-128/2950406086?p=0&ts=1668176745&t=8bd993dac2a1c6fcbed5adfae14b34df6c36d667&token=1668176745_ff8e5c3d9bcf8b4d2c3b14a12b25bc5bf3964bc8"}}},{"type":"album","name":"The Forgotten Winter","url":"https://wintersphere.bandcamp.com/album/the-forgotten-winter","imageUrl":"https://f4.bcbits.com/img/a2811913361_9.jpg","genre":"ambient","artist":{"name":"Winter Sphere","url":"https://wintersphere.bandcamp.com","imageUrl":"https://f4.bcbits.com/img/28342849_21.jpg"},"location":"Sweden","featuredTrack":{"name":"The Forgotten Winter (Side A)","duration":872,"streamUrl":{"mp3-128":"https://t4.bcbits.com/stream/c1538559d432cc1be4a46fa0ac7828b9/mp3-128/1935118209?p=0&ts=1668176745&t=2099c5dd03e0c5bb09c58e3aadbefa3d91d16da9&token=1668176745_041f16324968794653845568c0414dae48f48a7a"}}},{"type":"album","name":"Le Vitrail","url":"https://lamasz.bandcamp.com/album/le-vitrail","imageUrl":"https://f4.bcbits.com/img/a1453663789_9.jpg","genre":"ambient","artist":{"name":"Lamasz","url":"https://lamasz.bandcamp.com","imageUrl":"https://f4.bcbits.com/img/26178997_21.jpg"},"location":"Montreal, Québec","featuredTrack":{"name":"Maquette","duration":318,"streamUrl":{"mp3-128":"https://t4.bcbits.com/stream/293ac1f0ea9532bc4fd53c5fccbd39af/mp3-128/3672395257?p=0&ts=1668176745&t=1aef2c395009dbc6a27b5484e1d148e18108ac4e&token=1668176745_e6c818ffaaeb122b17461492c7b34c11905abdf0"}}},{"type":"album","name":"At The River Of Hell You're A Sparrow","url":"https://nonconnahordeath.bandcamp.com/album/at-the-river-of-hell-youre-a-sparrow","imageUrl":"https://f4.bcbits.com/img/a3247577113_9.jpg","genre":"ambient","artist":{"name":"Nonconnah","url":"https://nonconnahordeath.bandcamp.com","imageUrl":"https://f4.bcbits.com/img/30379141_21.jpg"},"location":"Memphis, Tennessee","featuredTrack":{"name":"As Though The Wheel Of Fate Were Passing Through The Ruins","duration":149.621,"streamUrl":{"mp3-128":"https://t4.bcbits.com/stream/8f6ca3e88fd9b58cf937f16adf7ee38f/mp3-128/2675336777?p=0&ts=1668176745&t=445230cbd6488e85d9db3efd5d641e6bcd726266&token=1668176745_f01b18b6ab050b5639323b7da1ed6848ed6aa5ee"}}},{"type":"album","name":"Periodic Function","url":"https://umerecords.bandcamp.com/album/periodic-function","imageUrl":"https://f4.bcbits.com/img/a3782497727_9.jpg","genre":"ambient","artist":{"name":"Munetoshi Nakayama","url":"https://umerecords.bandcamp.com","imageUrl":"https://f4.bcbits.com/img/14681400_21.jpg"},"location":"Tokyo, Japan","featuredTrack":{"name":"Wind Direction","duration":307.625,"streamUrl":{"mp3-128":"https://t4.bcbits.com/stream/6793504fa3804eb6494903aec67c80c9/mp3-128/2577536937?p=0&ts=1668176745&t=49085b8a64c9b20f9eee74c2e0133f32607a0856&token=1668176745_7c2e8ceaf1e271fcc9496300ca7bb223cfc2856a"}}},{"type":"album","name":"Autumn 2022","url":"https://eliovaresse.bandcamp.com/album/autumn-2022","imageUrl":"https://f4.bcbits.com/img/a3731606205_9.jpg","genre":"ambient","artist":{"name":"Elio Varesse","url":"https://eliovaresse.bandcamp.com","imageUrl":"https://f4.bcbits.com/img/20413276_21.jpg"},"location":"Spain","featuredTrack":{"name":"Sing a Song of Seasons","duration":388.901,"streamUrl":{"mp3-128":"https://t4.bcbits.com/stream/84141a2f67b14d79561f4027ab1845e5/mp3-128/3284479945?p=0&ts=1668176745&t=d660b260677f4c104ac01337fb78d4e3c02064ab&token=1668176745_9d03fe35b5e6d4da19c901ae2e6d57d5e4b1b183"}}},{"type":"album","name":"THESIS 20 - Isolarii","url":"https://thesisproject.bandcamp.com/album/thesis-20-isolarii","imageUrl":"https://f4.bcbits.com/img/a2337449375_9.jpg","genre":"ambient","artist":{"name":"Corey Fuller, Richard Skelton","url":"https://thesisproject.bandcamp.com","imageUrl":"https://f4.bcbits.com/img/15816800_21.jpg"},"location":"Saint Peter, Minnesota","featuredTrack":{"name":"Iland","duration":664.64,"streamUrl":{"mp3-128":"https://t4.bcbits.com/stream/bf0305126d6e35423e42cf001aaf5754/mp3-128/739871065?p=0&ts=1668176745&t=5ef2de99c1e3e2e75770604d329f0152d2442ed4&token=1668176745_e1d42ee64ad062398b3bc469fcb8d9b068763c95"}}},{"type":"album","name":"Rejet","url":"https://trehasektori.bandcamp.com/album/rejet","imageUrl":"https://f4.bcbits.com/img/a2407105835_9.jpg","genre":"ambient","artist":{"name":"Treha Sektori","url":"https://trehasektori.bandcamp.com","imageUrl":"https://f4.bcbits.com/img/26621977_21.jpg"},"location":"Paris, France","featuredTrack":{"name":"Sevorh Deh Armenh","duration":230.833,"streamUrl":{"mp3-128":"https://t4.bcbits.com/stream/a7ed3c9956d1c9ca7afab796e139c9cc/mp3-128/3689223018?p=0&ts=1668176745&t=fca6faf2d9a5d67c65d6e23ea3ede1fe476cf5da&token=1668176745_282681648c5ed9a18af361632cb11c220a7fb02e"}}},{"type":"album","name":"sojourn","url":"https://zarr.bandcamp.com/album/sojourn","imageUrl":"https://f4.bcbits.com/img/a3539022094_9.jpg","genre":"ambient","artist":{"name":"zarr.","url":"https://zarr.bandcamp.com","imageUrl":"https://f4.bcbits.com/img/26110599_21.jpg"},"location":"UK","featuredTrack":{"name":"Sojourn","duration":329,"streamUrl":{"mp3-128":"https://t4.bcbits.com/stream/d974b8e1155dbb1e491bd2eb890309f6/mp3-128/4011488883?p=0&ts=1668176745&t=73bf89d93820c65598fff4009c39cf1f1ebcfa83&token=1668176745_4186fe325734e700f49992e3cde818a66369d29f"}}},{"type":"album","name":"Céramique Électronique","url":"https://combustaolenta.bandcamp.com/album/c-ramique-lectronique","imageUrl":"https://f4.bcbits.com/img/a2740121476_9.jpg","genre":"ambient","artist":{"name":"Paulo Vicente","url":"https://combustaolenta.bandcamp.com","imageUrl":"https://f4.bcbits.com/img/12861760_21.jpg"},"location":"Lamego, Portugal","featuredTrack":{"name":"Tournasser","duration":500.613,"streamUrl":{"mp3-128":"https://t4.bcbits.com/stream/a1c0b3b8f061af9a898fda52bb2eb624/mp3-128/2971090573?p=0&ts=1668176745&t=6df362dedcb8a5ff71973b184d95b4ac32413082&token=1668176745_46868682f8a5ca23b9bb63c35c7e3de4b880e8d2"}}},{"type":"album","name":"Ray of Light","url":"https://elanvital.bandcamp.com/album/ray-of-light","imageUrl":"https://f4.bcbits.com/img/a1562474994_9.jpg","genre":"ambient","artist":{"name":"Saito Koji","url":"https://elanvital.bandcamp.com","imageUrl":"https://f4.bcbits.com/img/24637024_21.jpg"},"location":"North Macedonia","featuredTrack":{"name":"Ray of Light","duration":2400,"streamUrl":{"mp3-128":"https://t4.bcbits.com/stream/ee40b6b82f194ea492d7707dd1bc112e/mp3-128/3369189888?p=0&ts=1668176745&t=aa6f1e25c5bfe784c9f6e251c0b332851286b574&token=1668176745_6b4cc318ce53f980de7966727427d41758cee10a"}}},{"type":"album","name":"Going Steady","url":"https://northamericanszone.bandcamp.com/album/going-steady","imageUrl":"https://f4.bcbits.com/img/a2668844678_9.jpg","genre":"ambient","artist":{"name":"North Americans","url":"https://northamericanszone.bandcamp.com","imageUrl":"https://f4.bcbits.com/img/13952120_21.jpg"},"location":"Los Angeles, California","featuredTrack":{"name":"Going Steady","duration":267.622,"streamUrl":{"mp3-128":"https://t4.bcbits.com/stream/7213b2ac30c7542b2ad978a375d61d06/mp3-128/4114054886?p=0&ts=1668176745&t=0051abfecad0c2c1bb26c6ba3e06cfe828b5cce4&token=1668176745_786d773c2985f8947e9fef44f7d8ee1fd2eb6fd2"}}},{"type":"album","name":"Echoes of Songbird","url":"https://thelovelymoon.bandcamp.com/album/echoes-of-songbird","imageUrl":"https://f4.bcbits.com/img/a56119981_9.jpg","genre":"ambient","artist":{"name":"The Lovely Moon","url":"https://thelovelymoon.bandcamp.com","imageUrl":"https://f4.bcbits.com/img/20816132_21.jpg"},"location":"Manchester, UK","featuredTrack":{"name":"Echoes of Songbird","duration":1856.52,"streamUrl":{"mp3-128":"https://t4.bcbits.com/stream/027e1b0ec845b00cddba80499b19428c/mp3-128/1084321772?p=0&ts=1668176745&t=f012289ff367e7bffa7e911d4c6a69b63c892d60&token=1668176745_c40439f1b86cafdedd12149f5dcd2a2915b67d21"}}},{"type":"album","name":"Against the Sky","url":"https://anthene.bandcamp.com/album/against-the-sky","imageUrl":"https://f4.bcbits.com/img/a532660890_9.jpg","genre":"ambient","artist":{"name":"Rosales","url":"https://anthene.bandcamp.com","imageUrl":"https://f4.bcbits.com/img/26423286_21.jpg"},"location":"Toronto, Ontario","featuredTrack":{"name":"Austere","duration":298,"streamUrl":{"mp3-128":"https://t4.bcbits.com/stream/e727fc253fcb533c43a9566331671bde/mp3-128/4212945696?p=0&ts=1668176745&t=e43cb852a0e302ef5e58db31dd48f0c7f36d66ff&token=1668176745_b6b5eb9a739b267959d14afcab69d94accfe7d83"}}},{"type":"album","name":"Introspection - singles & rarities 1993-2000","url":"https://windyandcarl.bandcamp.com/album/introspection-singles-rarities-1993-2000","imageUrl":"https://f4.bcbits.com/img/a579756703_9.jpg","genre":"ambient","artist":{"name":"Windy Weber & Carl Hultgren","url":"https://windyandcarl.bandcamp.com","imageUrl":"https://f4.bcbits.com/img/15543191_21.jpg"},"location":"Dearborn, Michigan","featuredTrack":{"name":"Fragments Of Time And Space","duration":359.76,"streamUrl":{"mp3-128":"https://t4.bcbits.com/stream/eb0e3fe024fd2c78d23e6c5928161dd9/mp3-128/2337786499?p=0&ts=1668176745&t=a0ae00f73f54e4860dc0d091d1a15958c74bba65&token=1668176745_850b1531abbf54e17c31cbba44a93662fa2afd05"}}},{"type":"album","name":"Fallout 4","url":"https://darkroomtheband.bandcamp.com/album/fallout-4","imageUrl":"https://f4.bcbits.com/img/a2945227307_9.jpg","genre":"ambient","artist":{"name":"Darkroom","url":"https://darkroomtheband.bandcamp.com","imageUrl":"https://f4.bcbits.com/img/29650887_21.jpg"},"location":"UK","featuredTrack":{"name":"It's Clear From The Air","duration":942.862,"streamUrl":{"mp3-128":"https://t4.bcbits.com/stream/25a36c276b5e277c3a2bb5411081e8a1/mp3-128/1517955603?p=0&ts=1668176745&t=694efe6e03d8b868d6bd018af90cca4bb72bd73a&token=1668176745_1f2c687dff583ee35a6303ebac0ceca6eff588ab"}}},{"type":"album","name":"Occult Tapes","url":"https://desbot.bandcamp.com/album/occult-tapes","imageUrl":"https://f4.bcbits.com/img/a4172567199_9.jpg","genre":"ambient","artist":{"name":"Desbot","url":"https://desbot.bandcamp.com","imageUrl":"https://f4.bcbits.com/img/19381801_21.jpg"},"location":"Napier, New Zealand","featuredTrack":{"name":"In Waves","duration":330.43,"streamUrl":{"mp3-128":"https://t4.bcbits.com/stream/e22f3db5c890b6c681e71e184c4307ef/mp3-128/1898978703?p=0&ts=1668176745&t=28c6293dd158144456c438663a08e96222f75a3e&token=1668176745_434623fa21674771f40e32dee3d11955a3d364b7"}}},{"type":"album","name":"Deep Blue Universe","url":"https://deepspace1.bandcamp.com/album/deep-blue-universe","imageUrl":"https://f4.bcbits.com/img/a428217506_9.jpg","genre":"ambient","artist":{"name":"deepspace","url":"https://deepspace1.bandcamp.com","imageUrl":"https://f4.bcbits.com/img/28068548_21.jpg"},"location":"Brisbane, Australia","featuredTrack":{"name":"Hallucinogen 1 (And Now We May Dream)","duration":598,"streamUrl":{"mp3-128":"https://t4.bcbits.com/stream/f1656524768984c673c8edee034fdc73/mp3-128/2675741657?p=0&ts=1668176745&t=e232c76b7dd27d3965d04d13b02005e5253eaabd&token=1668176745_4880c85e057c54239a457a10c6faac5b27fdc777"}}},{"type":"album","name":"Extended (remastered)","url":"https://solarfields.bandcamp.com/album/extended-remastered","imageUrl":"https://f4.bcbits.com/img/a3555795820_9.jpg","genre":"ambient","artist":{"name":"Solar Fields","url":"https://solarfields.bandcamp.com","imageUrl":"https://f4.bcbits.com/img/3471719_21.jpg"},"location":"Sweden","featuredTrack":{"name":"Combinations (remastered)","duration":961.027,"streamUrl":{"mp3-128":"https://t4.bcbits.com/stream/ce2c56c7cca464b0b41442cf1c15d892/mp3-128/3789563812?p=0&ts=1668176745&t=8af9d9799713285f4562c9a910fa6405f1b53f73&token=1668176745_07c9ff235944c7c83fd2c61c141afb0f4912da38"}}},{"type":"album","name":"hidden wounds","url":"https://fraill.bandcamp.com/album/hidden-wounds","imageUrl":"https://f4.bcbits.com/img/a715167271_9.jpg","genre":"ambient","artist":{"name":"frail","url":"https://fraill.bandcamp.com","imageUrl":"https://f4.bcbits.com/img/29286936_21.jpg"},"location":"Minnesota","featuredTrack":{"name":"buried under worn bedsheets on a cold autumn morning","duration":315.455,"streamUrl":{"mp3-128":"https://t4.bcbits.com/stream/73fecbb36be509b570c44e28f709138f/mp3-128/1703390873?p=0&ts=1668176745&t=dd6479cf90d97bd3caee13e242e0cffe82142f4a&token=1668176745_20d63d95f1b79e5263333a5889e7c1638864d5cb"}}},{"type":"album","name":"Collection Lence","url":"https://startacker.bandcamp.com/album/collection-lence","imageUrl":"https://f4.bcbits.com/img/a3184328902_9.jpg","genre":"ambient","artist":{"name":"Startacker","url":"https://startacker.bandcamp.com","imageUrl":"https://f4.bcbits.com/img/30420310_21.jpg"},"location":"Colorado","featuredTrack":{"name":"A Haunting in DeVille (Which Means It's a Normal Sunday Evening)","duration":197.647,"streamUrl":{"mp3-128":"https://t4.bcbits.com/stream/23ef3aa4eb4589ab9b08f78ccbdf627e/mp3-128/2084570736?p=0&ts=1668176745&t=8a61a594aeb72039ee24396ef23795b3686fb5f6&token=1668176745_230077c288777019de11aaa89ffb87842d07e0e3"}}},{"type":"album","name":"sleepwalker","url":"https://shalloboi.bandcamp.com/album/sleepwalker","imageUrl":"https://f4.bcbits.com/img/a3197403281_9.jpg","genre":"ambient","artist":{"name":"shalloboi","url":"https://shalloboi.bandcamp.com","imageUrl":"https://f4.bcbits.com/img/665237_21.jpg"},"location":"Kansas City, Kansas","featuredTrack":{"name":"sleepwalker","duration":326,"streamUrl":{"mp3-128":"https://t4.bcbits.com/stream/8e670aba48ae863972fc453e01c62495/mp3-128/498022551?p=0&ts=1668176745&t=c1cada802a27855077dca4f801c844ad387d021d&token=1668176745_e327e2a030e2a915cd42b6341a9dbb42a89a86c1"}}},{"type":"album","name":"Floating Weeds","url":"https://tunnelwater.bandcamp.com/album/floating-weeds","imageUrl":"https://f4.bcbits.com/img/a3932189821_9.jpg","genre":"ambient","artist":{"name":"Tunnelwater","url":"https://tunnelwater.bandcamp.com","imageUrl":"https://f4.bcbits.com/img/16052298_21.jpg"},"location":"Ashford, UK","featuredTrack":{"name":"At The Harbour","duration":259.622,"streamUrl":{"mp3-128":"https://t4.bcbits.com/stream/4ed46d032c9ddb4c262f6985179df03e/mp3-128/342246542?p=0&ts=1668176745&t=508e8b090db8a42239cb08875dfb6238df66254a&token=1668176745_c26a865f7054d46495f34cc3ac3f7168441cf279"}}},{"type":"album","name":"The Sun Setting Into The Sea","url":"https://solarplexus.bandcamp.com/album/the-sun-setting-into-the-sea","imageUrl":"https://f4.bcbits.com/img/a1572577142_9.jpg","genre":"ambient","artist":{"name":"Solar Plexus","url":"https://solarplexus.bandcamp.com","imageUrl":"https://f4.bcbits.com/img/29651658_21.jpg"},"location":"Manchester, UK","featuredTrack":{"name":"The Sun Setting Into The Sea","duration":3351.18,"streamUrl":{"mp3-128":"https://t4.bcbits.com/stream/5d6d4fe8df0bd6115c854fed13f0d67f/mp3-128/786259873?p=0&ts=1668176745&t=c4268f84ebe342a820a3564b3648dcb8f9e74402&token=1668176745_7ac65c1cd3c7403ea5dee6488b56aa884b0938a3"}}},{"type":"album","name":"Furie","url":"https://innerwoud.bandcamp.com/album/furie","imageUrl":"https://f4.bcbits.com/img/a2463127043_9.jpg","genre":"ambient","artist":{"name":"Innerwoud","url":"https://innerwoud.bandcamp.com","imageUrl":"https://f4.bcbits.com/img/29948503_21.jpg"},"location":"Ghent, Belgium","featuredTrack":{"name":"Raseri","duration":839.292,"streamUrl":{"mp3-128":"https://t4.bcbits.com/stream/28a0887f87f7626c6c2f4baf68bb944c/mp3-128/2603163291?p=0&ts=1668176745&t=abd0d5f9850a9694eb81cff23956579109730633&token=1668176745_5164eb3105efba9b63a522d756eda18c46ff1b81"}}},{"type":"album","name":"Vetus Mundus","url":"https://torusdome.bandcamp.com/album/vetus-mundus","imageUrl":"https://f4.bcbits.com/img/a2207444525_9.jpg","genre":"ambient","artist":{"name":"Torus Dome","url":"https://torusdome.bandcamp.com","imageUrl":"https://f4.bcbits.com/img/27870956_21.jpg"},"location":"Turku, Finland","featuredTrack":{"name":"From Out The Ruins","duration":299.096,"streamUrl":{"mp3-128":"https://t4.bcbits.com/stream/7cdad6eb75c7bbb470cb0ca69696cbcf/mp3-128/1489906819?p=0&ts=1668176745&t=92fca8542de650030a04a8f0b0010562756e5736&token=1668176745_bdee6160cf22ee51c2bbd881ae75546cb591cd70"}}},{"type":"album","name":"Echoes in the Valley Vol. 6","url":"https://eitvrecords.bandcamp.com/album/echoes-in-the-valley-vol-6","imageUrl":"https://f4.bcbits.com/img/a2512436629_9.jpg","genre":"ambient","artist":{"name":"Echoes in the Valley","url":"https://eitvrecords.bandcamp.com","imageUrl":"https://f4.bcbits.com/img/26440916_21.jpg"},"location":"Australia","featuredTrack":{"name":"Dependent","duration":192.914,"streamUrl":{"mp3-128":"https://t4.bcbits.com/stream/f95ff0cb486838f9852e678cfbd16638/mp3-128/1928117663?p=0&ts=1668176745&t=e3f2897e5020a31f428b313b7fde095bc27e5d51&token=1668176745_e3c73998efe7e2719d864363c1b864f804203032"}}},{"type":"album","name":"All My People","url":"https://mariasomerville.bandcamp.com/album/all-my-people","imageUrl":"https://f4.bcbits.com/img/a3741993361_9.jpg","genre":"ambient","artist":{"name":"Maria Somerville","url":"https://mariasomerville.bandcamp.com","imageUrl":"https://f4.bcbits.com/img/15077542_21.jpg"},"location":"Galway, Ireland","featuredTrack":{"name":"Eyes Don't Say It","duration":197,"streamUrl":{"mp3-128":"https://t4.bcbits.com/stream/32e46d408e252c79a1e12ad6fae2b899/mp3-128/1704852676?p=0&ts=1668176745&t=b3356bfe357ddf3dfdecdfe57ff7b7f3be8dc6ac&token=1668176745_589eeb13c54d8886ee70a230f344c3fe29ceae78"}}},{"type":"album","name":"Deep in Ocean Sunk the Lamp of Light","url":"https://aethenor.bandcamp.com/album/deep-in-ocean-sunk-the-lamp-of-light","imageUrl":"https://f4.bcbits.com/img/a2646791745_9.jpg","genre":"ambient","artist":{"name":"Æthenor","url":"https://aethenor.bandcamp.com","imageUrl":"https://f4.bcbits.com/img/8178743_21.jpg"},"location":"London, UK","featuredTrack":{"name":"Deep in Ocean Sunk the Lamp of Light Pt. 1","duration":609.16,"streamUrl":{"mp3-128":"https://t4.bcbits.com/stream/334a131204971ac456555b7fb9639990/mp3-128/2686577733?p=0&ts=1668176745&t=f7c9c6db30bbb07b65828b862d0857fa0bc3d2bc&token=1668176745_5b288fe508921253f7f6978ab21bb5a4f449ad9f"}}},{"type":"album","name":"In the Dark Palaces of Both Our Hearts","url":"https://yulyseus.bandcamp.com/album/in-the-dark-palaces-of-both-our-hearts","imageUrl":"https://f4.bcbits.com/img/a497499233_9.jpg","genre":"ambient","artist":{"name":"YULYSEUS","url":"https://yulyseus.bandcamp.com","imageUrl":"https://f4.bcbits.com/img/18466963_21.jpg"},"location":"Glasgow, UK","featuredTrack":{"name":"In the Dark Palaces of Both Our Hearts","duration":555.938,"streamUrl":{"mp3-128":"https://t4.bcbits.com/stream/9552cf6cc8d3f79c49cb0afb4ecad870/mp3-128/1112241358?p=0&ts=1668176745&t=55b2b45fcd5634c925876d5fd15448f3585d3e8e&token=1668176745_14bc656fa2435c6ded4a67b41c2c800d4061feed"}}},{"type":"album","name":"A Magic Spin EP","url":"https://janniscarbotta.bandcamp.com/album/a-magic-spin-ep","imageUrl":"https://f4.bcbits.com/img/a751517426_9.jpg","genre":"ambient","artist":{"name":"Jannis Carbotta","url":"https://janniscarbotta.bandcamp.com","imageUrl":"https://f4.bcbits.com/img/30211214_21.jpg"},"location":"Cologne, Germany","featuredTrack":{"name":"A Magic Spin","duration":220.701,"streamUrl":{"mp3-128":"https://t4.bcbits.com/stream/7782a105df3d904841b06aeece32c2c9/mp3-128/1997858122?p=0&ts=1668176745&t=824aa71880250053c37541f041eb9ac9cb554732&token=1668176745_948afff6646559456c5f0c8328f918938f858eb5"}}},{"type":"album","name":"So Extra Bronze Lamp","url":"https://imaginarysoftwoods.bandcamp.com/album/so-extra-bronze-lamp","imageUrl":"https://f4.bcbits.com/img/a2796927151_9.jpg","genre":"ambient","artist":{"name":"Imaginary Softwoods","url":"https://imaginarysoftwoods.bandcamp.com","imageUrl":"https://f4.bcbits.com/img/19611998_21.jpg"},"location":"Cleveland, Ohio","featuredTrack":{"name":"Innerglow Portal/Aqua Drawer Lamp","duration":525.195,"streamUrl":{"mp3-128":"https://t4.bcbits.com/stream/d67813807a7700bb238219e5b7e65fe6/mp3-128/4042431815?p=0&ts=1668176745&t=cbe6fefeee2a46e246583ba4f9856b1bb28a0b3e&token=1668176745_6e253382ec4e8540e05f087ef015e4aea46afe97"}}},{"type":"album","name":"listening air","url":"https://anthene.bandcamp.com/album/listening-air","imageUrl":"https://f4.bcbits.com/img/a1596350206_9.jpg","genre":"ambient","artist":{"name":"anthéne","url":"https://anthene.bandcamp.com","imageUrl":"https://f4.bcbits.com/img/26423286_21.jpg"},"location":"Toronto, Ontario","featuredTrack":{"name":"we are","duration":592.679,"streamUrl":{"mp3-128":"https://t4.bcbits.com/stream/648ccaa5cfd4d8c2551fca4f22f71a37/mp3-128/457461856?p=0&ts=1668176745&t=c3186bd27e6412092dab928f37bf026e03d033b1&token=1668176745_9a63f37ade0376da829ba8452e6bfbe96d466b31"}}},{"type":"album","name":"Burnt Atlas III","url":"https://vibratelepathos.bandcamp.com/album/burnt-atlas-iii","imageUrl":"https://f4.bcbits.com/img/a1610917068_9.jpg","genre":"ambient","artist":{"name":"Milieu","url":"https://vibratelepathos.bandcamp.com","imageUrl":"https://f4.bcbits.com/img/24316877_21.jpg"},"location":"Dayton, Ohio","featuredTrack":{"name":"Burnt Atlas III","duration":3783.71,"streamUrl":{"mp3-128":"https://t4.bcbits.com/stream/a29806539fb8b65a20a42dcb7204df89/mp3-128/281542279?p=0&ts=1668176745&t=2d4d1fbac93331c64af0ff53518ddd3b090b2d64&token=1668176745_4b9117d9d1f143646dabc806d91f3de88a5a27b4"}}},{"type":"album","name":"Dipping Pools","url":"https://ambisolace.bandcamp.com/album/dipping-pools","imageUrl":"https://f4.bcbits.com/img/a2684890571_9.jpg","genre":"ambient","artist":{"name":"Ambisolace","url":"https://ambisolace.bandcamp.com","imageUrl":"https://f4.bcbits.com/img/29187779_21.jpg"},"location":"Berlin, Germany","featuredTrack":{"name":"Light Rain on an Ocean of Calm","duration":1227.05,"streamUrl":{"mp3-128":"https://t4.bcbits.com/stream/17ce900767e9e6433204fbe632184ff4/mp3-128/940313070?p=0&ts=1668176745&t=5f2c7232234db72b054f20c89202db3011c09808&token=1668176745_0d3caa6acc64ae7daaa2bfc8f16c1686cc4b6e25"}}},{"type":"album","name":"World Receiver","url":"https://infraction.bandcamp.com/album/world-receiver","imageUrl":"https://f4.bcbits.com/img/a925691271_9.jpg","genre":"ambient","artist":{"name":"Tetsu Inoue","url":"https://infraction.bandcamp.com","imageUrl":"https://f4.bcbits.com/img/26449141_21.jpg"},"location":null,"featuredTrack":{"name":"Health Loop","duration":498.2,"streamUrl":{"mp3-128":"https://t4.bcbits.com/stream/8927182d97bd908ab9eddde8780caf7c/mp3-128/3854395241?p=0&ts=1668176745&t=1065f0ffa9c768b9ab0b539b9af07b6873cc0c2c&token=1668176745_196df871c4ee9ea1cbd794ffae0b62874f6e4461"}}},{"type":"album","name":"Allures","url":"https://nouvellegaze.bandcamp.com/album/allures","imageUrl":"https://f4.bcbits.com/img/a2390231145_9.jpg","genre":"ambient","artist":{"name":"White Stains","url":"https://nouvellegaze.bandcamp.com","imageUrl":"https://f4.bcbits.com/img/23841835_21.jpg"},"location":"UK","featuredTrack":{"name":"Second Journey","duration":226.002,"streamUrl":{"mp3-128":"https://t4.bcbits.com/stream/777470c57991976780e60fe2943683c9/mp3-128/3972544323?p=0&ts=1668176745&t=55006ad7a4e1586164ff8b7b3b0561bf445d61ef&token=1668176745_2143c801aee53341997ebfacd0f83dfacad6538f"}}},{"type":"album","name":"univocal","url":"https://obalto.bandcamp.com/album/univocal","imageUrl":"https://f4.bcbits.com/img/a2206097387_9.jpg","genre":"ambient","artist":{"name":"Shuta Hiraki","url":"https://obalto.bandcamp.com","imageUrl":"https://f4.bcbits.com/img/28972639_21.jpg"},"location":"Japan","featuredTrack":{"name":"on baluster","duration":921.25,"streamUrl":{"mp3-128":"https://t4.bcbits.com/stream/e13d2a5b1fc11adb66888511face6c03/mp3-128/1587083838?p=0&ts=1668176745&t=db6770a584a47ccdc3fd0b27001e05f505eb13f9&token=1668176745_a5fdd2fdbc201b58eefff487263444b050491cc2"}}},{"type":"album","name":"Andarlīh","url":"https://hymnambulae.bandcamp.com/album/andarl-h","imageUrl":"https://f4.bcbits.com/img/a555057242_9.jpg","genre":"ambient","artist":{"name":"Hymnambulae","url":"https://hymnambulae.bandcamp.com","imageUrl":"https://f4.bcbits.com/img/20324830_21.jpg"},"location":"Umeå, Sweden","featuredTrack":{"name":"Light-Vessel","duration":292.429,"streamUrl":{"mp3-128":"https://t4.bcbits.com/stream/7682b1b878c4bc531c0f5e79af4da001/mp3-128/1899363714?p=0&ts=1668176745&t=016c09525dbbbdc5e1f63159ebda19d217cd970d&token=1668176745_997c71d07eb7dfc52ed79c3ab85324357d3c9da3"}}},{"type":"album","name":"Desert Soundscapes","url":"https://cecilpurihin.bandcamp.com/album/desert-soundscapes","imageUrl":"https://f4.bcbits.com/img/a581333676_9.jpg","genre":"ambient","artist":{"name":"Cecil Purihin","url":"https://cecilpurihin.bandcamp.com","imageUrl":"https://f4.bcbits.com/img/28653656_21.jpg"},"location":"Las Vegas, Nevada","featuredTrack":{"name":"Warm","duration":664.957,"streamUrl":{"mp3-128":"https://t4.bcbits.com/stream/fe8144eca01cc9f503b20e8829e0e184/mp3-128/2518595303?p=0&ts=1668176745&t=6d3dd47d3153f173a7f96482c13379dea762d74e&token=1668176745_f137a4ed5e4a1cb1fe926beb0b11a5b33780845e"}}},{"type":"album","name":"歌の続きが決まったら（uta）","url":"https://kunugi.bandcamp.com/album/uta","imageUrl":"https://f4.bcbits.com/img/a2461363275_9.jpg","genre":"ambient","artist":{"name":"Kunugi","url":"https://kunugi.bandcamp.com","imageUrl":"https://f4.bcbits.com/img/16239969_21.jpg"},"location":"Tokyo, Japan","featuredTrack":{"name":"日陰（shade）","duration":277.5,"streamUrl":{"mp3-128":"https://t4.bcbits.com/stream/c5f5dd11cd349c2f7e61377ce36b2075/mp3-128/4158229987?p=0&ts=1668176745&t=b1629f92d9a0cc1a838504f95c6d7d2a03da0cdc&token=1668176745_3878d41965d3cf55677416e859698cc58ea462ff"}}},{"type":"album","name":"Sin City","url":"https://musiquemoleculaire.bandcamp.com/album/sin-city","imageUrl":"https://f4.bcbits.com/img/a2391498438_9.jpg","genre":"ambient","artist":{"name":"Ratel Furax","url":"https://musiquemoleculaire.bandcamp.com","imageUrl":"https://f4.bcbits.com/img/24424895_21.jpg"},"location":"Montreal, Québec","featuredTrack":{"name":"If You're Stoned Enough","duration":336.537,"streamUrl":{"mp3-128":"https://t4.bcbits.com/stream/b589bb9dd66a96c7a58a9958041e5bdd/mp3-128/2267464994?p=0&ts=1668176745&t=1beaf1096359f755a402977c07e42798705a984a&token=1668176745_a49508e72d9d656854cb807263e68f968817c9e5"}}},{"type":"album","name":"Portals","url":"https://forrestdrones.bandcamp.com/album/portals","imageUrl":"https://f4.bcbits.com/img/a478908960_9.jpg","genre":"ambient","artist":{"name":"Forrest","url":"https://forrestdrones.bandcamp.com","imageUrl":"https://f4.bcbits.com/img/19704567_21.jpg"},"location":"Vancouver, Washington","featuredTrack":{"name":"Pale Rider","duration":330.2,"streamUrl":{"mp3-128":"https://t4.bcbits.com/stream/e5277c4c05c807ba60c89bbca3944144/mp3-128/3288487660?p=0&ts=1668176745&t=c14ecf8687ee616dfd176c8a6962674871e179ee&token=1668176745_c454581e6d275f917fe5ea063449fc32038b2dee"}}},{"type":"album","name":"Ephemeralis Algorithmica","url":"https://jacobnewman.bandcamp.com/album/ephemeralis-algorithmica","imageUrl":"https://f4.bcbits.com/img/a245103748_9.jpg","genre":"ambient","artist":{"name":"Jacob Newman","url":"https://jacobnewman.bandcamp.com","imageUrl":"https://f4.bcbits.com/img/10203988_21.jpg"},"location":"Colorado","featuredTrack":{"name":"Nubia in Dreams","duration":363.156,"streamUrl":{"mp3-128":"https://t4.bcbits.com/stream/b7891cd06fe95f04e09e5b0f36f01660/mp3-128/2233062092?p=0&ts=1668176745&t=3e54cfa8b21c75c53484816e18f061ce38432920&token=1668176745_e3967fa7f5e1b8d02bf310342762c6d74f6778e8"}}},{"type":"album","name":"Crow Covert","url":"https://riverrun.bandcamp.com/album/crow-covert","imageUrl":"https://f4.bcbits.com/img/a854130445_9.jpg","genre":"ambient","artist":{"name":"riverrun","url":"https://riverrun.bandcamp.com","imageUrl":"https://f4.bcbits.com/img/27398600_21.jpg"},"location":"England, UK","featuredTrack":{"name":"Crow Covert","duration":465.147,"streamUrl":{"mp3-128":"https://t4.bcbits.com/stream/944228f58926851711ae7d7a228c066c/mp3-128/2227060851?p=0&ts=1668176745&t=295d9c7b7a4f967332f319cc58d9825f1704ae66&token=1668176745_0688a17dcf65f4afb49a95391aa43ae3ee6661a8"}}},{"type":"album","name":"Tempus Clausum Cuntata (Cunty Little Hornets - I, II, III & IV)","url":"https://heronsuicide.bandcamp.com/album/tempus-clausum-cuntata-cunty-little-hornets-i-ii-iii-iv","imageUrl":"https://f4.bcbits.com/img/a182121038_9.jpg","genre":"ambient","artist":{"name":"Heron Suicide & Ian Curtisnt","url":"https://heronsuicide.bandcamp.com","imageUrl":"https://f4.bcbits.com/img/28317738_21.jpg"},"location":"England, UK","featuredTrack":{"name":"Cunty Little Hornets Part I (Typo - Negative)","duration":1126.5,"streamUrl":{"mp3-128":"https://t4.bcbits.com/stream/d28a3f6c3af6a00d060228f8a72f59fb/mp3-128/1446117311?p=0&ts=1668176745&t=7634f4f0fd7257f3cc501156fd1e5dad9f139141&token=1668176745_0276e67c8ccc16ecd1a35d486ff0b0bf1dbb6a56"}}}],"total":1177,"params":{"genre":"ambient","sortBy":"top","page":10,"subgenre":"drone","location":"0","format":"all"}}